{
	"info": {
		"_postman_id": "4a10ace4-2def-4248-8160-dcb8f2b734ac",
		"name": "Clase-Parcial2",
		"schema": "https://schema.getpostman.com/json/collection/v2.1.0/collection.json",
		"_exporter_id": "25935145"
	},
	"item": [
		{
			"name": "Add a clase",
			"event": [
				{
					"listen": "test",
					"script": {
						"exec": [
							"var data = pm.response.json()\r",
							"pm.globals.set(\"clase_id\", data.id);\r",
							"\r",
							"pm.test(\"Status code is 201\", function () {\r",
							"   pm.response.to.have.status(201);\r",
							"});"
						],
						"type": "text/javascript",
						"packages": {}
					}
				}
			],
			"request": {
				"method": "POST",
				"header": [],
				"body": {
					"mode": "raw",
					"raw": "{\r\n    \"nombre\": \"example\",\r\n    \"codigo\": \"1234567890\",\r\n    \"numero_creditos\": 3\r\n}",
					"options": {
						"raw": {
							"language": "json"
						}
					}
				},
				"url": {
					"raw": "{{baseURL}}/clase",
					"host": [
						"{{baseURL}}"
					],
					"path": [
						"clase"
					]
				}
			},
			"response": [
				{
					"name": "Add a clase",
					"originalRequest": {
						"method": "POST",
						"header": [],
						"body": {
							"mode": "raw",
							"raw": "{\r\n    \"nombre\": \"example\",\r\n    \"codigo\": \"1234567890\",\r\n    \"numero_creditos\": 3\r\n}",
							"options": {
								"raw": {
									"language": "json"
								}
							}
						},
						"url": {
							"raw": "{{baseURL}}/clase",
							"host": [
								"{{baseURL}}"
							],
							"path": [
								"clase"
							]
						}
					},
					"status": "Created",
					"code": 201,
					"_postman_previewlanguage": "json",
					"header": [
						{
							"key": "X-Powered-By",
							"value": "Express"
						},
						{
							"key": "Content-Type",
							"value": "application/json; charset=utf-8"
						},
						{
							"key": "Content-Length",
							"value": "106"
						},
						{
							"key": "ETag",
							"value": "W/\"6a-zIArKjctYEkI33yi05Few6I4HZQ\""
						},
						{
							"key": "Date",
							"value": "Sat, 30 Nov 2024 22:53:09 GMT"
						},
						{
							"key": "Connection",
							"value": "keep-alive"
						},
						{
							"key": "Keep-Alive",
							"value": "timeout=5"
						}
					],
					"cookie": [],
					"body": "{\n    \"nombre\": \"example\",\n    \"codigo\": \"1234567890\",\n    \"numero_creditos\": 3,\n    \"id\": \"0819b9a2-a682-4101-8453-22d99ec24d17\"\n}"
				}
			]
		},
		{
			"name": "Add an invalid clase (code length<10)",
			"event": [
				{
					"listen": "test",
					"script": {
						"exec": [
							"pm.test(\"Status code is 400\", function () {\r",
							"   pm.response.to.have.status(400);\r",
							"});\r",
							"\r",
							"pm.test(\"Get expected error message\", function () {\r",
							"   var data = pm.response.json();\r",
							"   pm.expect(data.message).to.eql(\"El codigo debe tener 10 caracteres\");\r",
							"});"
						],
						"type": "text/javascript",
						"packages": {}
					}
				}
			],
			"request": {
				"method": "POST",
				"header": [],
				"body": {
					"mode": "raw",
					"raw": "{\r\n    \"nombre\": \"example\",\r\n    \"codigo\": \"123\",\r\n    \"numero_creditos\": 3\r\n}",
					"options": {
						"raw": {
							"language": "json"
						}
					}
				},
				"url": {
					"raw": "{{baseURL}}/clase",
					"host": [
						"{{baseURL}}"
					],
					"path": [
						"clase"
					]
				}
			},
			"response": [
				{
					"name": "Add a clase Copy",
					"originalRequest": {
						"method": "POST",
						"header": [],
						"body": {
							"mode": "raw",
							"raw": "{\r\n    \"nombre\": \"example\",\r\n    \"codigo\": \"123\",\r\n    \"numero_creditos\": 3\r\n}",
							"options": {
								"raw": {
									"language": "json"
								}
							}
						},
						"url": {
							"raw": "{{baseURL}}/clase",
							"host": [
								"{{baseURL}}"
							],
							"path": [
								"clase"
							]
						}
					},
					"status": "Bad Request",
					"code": 400,
					"_postman_previewlanguage": "json",
					"header": [
						{
							"key": "X-Powered-By",
							"value": "Express"
						},
						{
							"key": "Content-Type",
							"value": "application/json; charset=utf-8"
						},
						{
							"key": "Content-Length",
							"value": "65"
						},
						{
							"key": "ETag",
							"value": "W/\"41-qv8SAJHMQCa2Tz/Zphby5lGnMcI\""
						},
						{
							"key": "Date",
							"value": "Sat, 30 Nov 2024 22:56:01 GMT"
						},
						{
							"key": "Connection",
							"value": "keep-alive"
						},
						{
							"key": "Keep-Alive",
							"value": "timeout=5"
						}
					],
					"cookie": [],
					"body": "{\n    \"statusCode\": 400,\n    \"message\": \"El codigo debe tener 10 caracteres\"\n}"
				}
			]
		},
		{
			"name": "Get one clase",
			"event": [
				{
					"listen": "test",
					"script": {
						"exec": [
							"pm.test(\"Status code is 200\", function () {\r",
							"   pm.response.to.have.status(200);\r",
							"});"
						],
						"type": "text/javascript",
						"packages": {}
					}
				}
			],
			"request": {
				"method": "GET",
				"header": [],
				"url": {
					"raw": "{{baseURL}}/clase/0819b9a2-a682-4101-8453-22d99ec24d17",
					"host": [
						"{{baseURL}}"
					],
					"path": [
						"clase",
						"0819b9a2-a682-4101-8453-22d99ec24d17"
					]
				}
			},
			"response": [
				{
					"name": "Get one clase",
					"originalRequest": {
						"method": "GET",
						"header": [],
						"url": {
							"raw": "{{baseURL}}/clase/0819b9a2-a682-4101-8453-22d99ec24d17",
							"host": [
								"{{baseURL}}"
							],
							"path": [
								"clase",
								"0819b9a2-a682-4101-8453-22d99ec24d17"
							]
						}
					},
					"status": "OK",
					"code": 200,
					"_postman_previewlanguage": "json",
					"header": [
						{
							"key": "X-Powered-By",
							"value": "Express"
						},
						{
							"key": "Content-Type",
							"value": "application/json; charset=utf-8"
						},
						{
							"key": "Content-Length",
							"value": "117"
						},
						{
							"key": "ETag",
							"value": "W/\"75-nrYK+sB/sQENBLaFP0LOGwbFcL8\""
						},
						{
							"key": "Date",
							"value": "Sat, 30 Nov 2024 22:53:27 GMT"
						},
						{
							"key": "Connection",
							"value": "keep-alive"
						},
						{
							"key": "Keep-Alive",
							"value": "timeout=5"
						}
					],
					"cookie": [],
					"body": "{\n    \"id\": \"0819b9a2-a682-4101-8453-22d99ec24d17\",\n    \"nombre\": \"example\",\n    \"codigo\": \"1234567890\",\n    \"numero_creditos\": 3,\n    \"bonos\": []\n}"
				}
			]
		},
		{
			"name": "Get an invalid clase",
			"event": [
				{
					"listen": "test",
					"script": {
						"exec": [
							"pm.test(\"Status code is 404\", function () {\r",
							"   pm.response.to.have.status(404);\r",
							"});\r",
							"\r",
							"pm.test(\"Get expected error message\", function () {\r",
							"   var data = pm.response.json();\r",
							"   pm.expect(data.message).to.eql(\"Clase con id 00000000-0000-0000-0000-000000000000 no encontrada\");\r",
							"});"
						],
						"type": "text/javascript",
						"packages": {}
					}
				}
			],
			"request": {
				"method": "GET",
				"header": [],
				"url": {
					"raw": "{{baseURL}}/clase/00000000-0000-0000-0000-000000000000",
					"host": [
						"{{baseURL}}"
					],
					"path": [
						"clase",
						"00000000-0000-0000-0000-000000000000"
					]
				}
			},
			"response": [
				{
					"name": "Get one clase Copy",
					"originalRequest": {
						"method": "GET",
						"header": [],
						"url": {
							"raw": "{{baseURL}}/clase/00000000-0000-0000-0000-000000000000",
							"host": [
								"{{baseURL}}"
							],
							"path": [
								"clase",
								"00000000-0000-0000-0000-000000000000"
							]
						}
					},
					"status": "Not Found",
					"code": 404,
					"_postman_previewlanguage": "json",
					"header": [
						{
							"key": "X-Powered-By",
							"value": "Express"
						},
						{
							"key": "Content-Type",
							"value": "application/json; charset=utf-8"
						},
						{
							"key": "Content-Length",
							"value": "94"
						},
						{
							"key": "ETag",
							"value": "W/\"5e-Wnk90FN0lzVXw2njjDvE0gWHmXo\""
						},
						{
							"key": "Date",
							"value": "Sat, 30 Nov 2024 22:54:26 GMT"
						},
						{
							"key": "Connection",
							"value": "keep-alive"
						},
						{
							"key": "Keep-Alive",
							"value": "timeout=5"
						}
					],
					"cookie": [],
					"body": "{\n    \"statusCode\": 404,\n    \"message\": \"Clase con id 00000000-0000-0000-0000-000000000000 no encontrada\"\n}"
				}
			]
		}
	],
	"event": [
		{
			"listen": "prerequest",
			"script": {
				"type": "text/javascript",
				"packages": {},
				"exec": [
					""
				]
			}
		},
		{
			"listen": "test",
			"script": {
				"type": "text/javascript",
				"packages": {},
				"exec": [
					""
				]
			}
		}
	],
	"variable": [
		{
			"key": "baseURL",
			"value": "http://localhost:3000/api/v1",
			"type": "string"
		},
		{
			"key": "clase_id",
			"value": "0",
			"type": "string"
		}
	]
}